README.md
ctnas/__init__.py
ctnas/api.py
ctnas/themes.py
pyproject.toml
ctnas-0.2.0.dist-info/WHEEL
ctnas-0.2.0.dist-info/METADATA
ctnas-0.2.0.dist-info/RECORD
