Metadata-Version: 2.1
Name: ctnas
Version: 0.2.0
Summary: 
Home-page: https://github.com/innvariant/ctnas
License: MIT
Keywords: neural architecture search,hidden structural prior,automated machine learning,neural network structure,neural graph
Author: Julian Stier
Author-email: julian.stier@uni-passau.de
Requires-Python: >=3.8,<4.0
Classifier: License :: OSI Approved :: MIT License
Classifier: Programming Language :: Python :: 3
Classifier: Programming Language :: Python :: 3.10
Classifier: Programming Language :: Python :: 3.8
Classifier: Programming Language :: Python :: 3.9
Requires-Dist: deepstruct (>=0.8.0,<0.9.0)
Requires-Dist: joblib (>=1.1.0,<2.0.0)
Requires-Dist: networkx (>=2.7.1,<3.0.0)
Requires-Dist: pandas (>=1.4.1,<2.0.0)
Requires-Dist: s3fs (>=2022.2.0,<2023.0.0)
Project-URL: Repository, https://github.com/innvariant/ctnas
